pydbtools-5.8.1.dist-info/METADATA
pydbtools-5.8.1.dist-info/WHEEL
pydbtools-5.8.1.dist-info/entry_points.txt
pydbtools/__init__.py
pydbtools/_sql_render.py
pydbtools/_wrangler.py
pydbtools/utils.py
pydbtools-5.8.1.dist-info/RECORD
