Metadata-Version: 2.1
Name: pydbtools
Version: 5.8.1
Summary: A python package to query data via amazon athena and bring it into a pandas df using aws-wrangler.
Author-Email: Karik Isichei <karik.isichei@digital.justice.gov.uk>
License: MIT
Requires-Python: <4.0,>=3.10
Requires-Dist: boto3>=1.7.4
Requires-Dist: sqlparse>=0.5.0
Requires-Dist: awswrangler>=2.12.0
Requires-Dist: pyarrow>=14.0.0
Requires-Dist: Jinja2>=3.1.0
Requires-Dist: sql-metadata<3.0.0,>=2.3.0
Requires-Dist: arrow-pd-parser>=1.3.9
